<?xml version="1.0" encoding="utf-8"?>
<!DOCTYPE hibernate-mapping PUBLIC "-//Hibernate/Hibernate Mapping DTD 3.0//EN"
"http://hibernate.sourceforge.net/hibernate-mapping-3.0.dtd">
<!-- 
    Mapping file autogenerated by MyEclipse Persistence Tools
-->
<hibernate-mapping>
    <class name="com.model.ReportFlowRule" table="ReportFlowRule" schema="dbo" catalog="REDB">
        <id name="rfId" type="java.lang.Integer">
            <column name="RF_Id" />
            <generator class="assigned" />
        </id>
        <property name="rfFlowId" type="java.lang.String">
            <column name="RF_flowId" length="50" not-null="true" />
        </property>
        <property name="rfFlowStatus" type="java.lang.String">
            <column name="RF_flowStatus" length="20" not-null="true" />
        </property>
        <property name="rfFlowExplain" type="java.lang.String">
            <column name="RF_flowExplain" length="50" not-null="true" />
        </property>
        <property name="rfBackStatus" type="java.lang.String">
            <column name="RF_backStatus" length="20" not-null="true" />
        </property>
        <property name="rfNextStatus" type="java.lang.String">
            <column name="RF_nextStatus" length="20" not-null="true" />
        </property>
        <property name="rfDepartment" type="java.lang.String">
            <column name="RF_department" length="20" not-null="true" />
        </property>
        <property name="rfRole" type="java.lang.String">
            <column name="RF_role" length="20" not-null="true" />
        </property>
        <property name="rfRemark" type="java.lang.String">
            <column name="RF_remark" length="1000" />
        </property>
        <property name="rfAction" type="java.lang.String">
            <column name="RF_action" length="50" />
        </property>
        <property name="rfActionUrl" type="java.lang.String">
            <column name="RF_actionUrl" length="100" />
        </property>
        <property name="rfTransitionFlag" type="java.lang.Integer">
            <column name="RF_transitionFlag" />
        </property>
        <property name="rfFlowImage" type="java.lang.String">
            <column name="RF_flowImage" length="255"/>
        </property>
    </class>
</hibernate-mapping>
